odoo/addons/website_addthis/README.rst
odoo/addons/website_addthis/__init__.py
odoo/addons/website_addthis/__manifest__.py
odoo/addons/website_addthis/i18n/website_addthis.pot
odoo/addons/website_addthis/models/__init__.py
odoo/addons/website_addthis/models/website.py
odoo/addons/website_addthis/models/website_config_settings.py
odoo/addons/website_addthis/readme/CONFIGURE.rst
odoo/addons/website_addthis/readme/CONTRIBUTORS.rst
odoo/addons/website_addthis/readme/DESCRIPTION.rst
odoo/addons/website_addthis/readme/USAGE.rst
odoo/addons/website_addthis/readme/images/addthis-adv-config.png
odoo/addons/website_addthis/static/description/icon.png
odoo/addons/website_addthis/static/description/index.html
odoo/addons/website_addthis/templates/layout.xml
odoo/addons/website_addthis/views/website.xml
odoo/addons/website_addthis/views/website_config_settings.xml
odoo11_addon_website_addthis-11.0.1.0.0.99.dev12.dist-info/METADATA
odoo11_addon_website_addthis-11.0.1.0.0.99.dev12.dist-info/WHEEL
odoo11_addon_website_addthis-11.0.1.0.0.99.dev12.dist-info/top_level.txt
odoo11_addon_website_addthis-11.0.1.0.0.99.dev12.dist-info/RECORD
